biblium/__init__.py
biblium/base.py
biblium/batch.py
biblium/bibclass.py
biblium/bibgroup.py
biblium/biblium_main.py
biblium/bibplot.py
biblium/bibstats.py
biblium/bibtkinter_app.py
biblium/citation_patterns.py
biblium/citation_velocity.py
biblium/colors.py
biblium/compare_means.py
biblium/concept_extraction.py
biblium/config.py
biblium/correlation.py
biblium/crosstabs.py
biblium/dedup.py
biblium/disruption.py
biblium/diversity.py
biblium/enhancements.py
biblium/lazy.py
biblium/llm_utils.py
biblium/logging_config.py
biblium/main_path.py
biblium/normalization.py
biblium/openalex_api.py
biblium/plotbib.py
biblium/readbib.py
biblium/reference_diversity.py
biblium/report_styles.py
biblium/reportbib.py
biblium/representation.py
biblium/sdg_identifier.py
biblium/utilsbib.py
biblium/additional files/PA_concepts.xlsx
biblium/additional files/Scopus_SDG_metadata.xlsx
biblium/additional files/Scopus_metadata.xlsx
biblium/additional files/countries.xlsx
biblium/additional files/language dictionary.xlsx
biblium/additional files/mappings.xlsx
biblium/additional files/readme.txt
biblium/additional files/scopus subject area codes.xlsx
biblium/additional files/sources_data_short.xlsx
biblium/additional files/stopwords.xlsx
biblium/additional files/template for excel output.xlsx
biblium/additional files/template for group report output.xlsx
biblium/additional files/template for powerpoint output.xlsx
biblium/additional files/template for report output.xlsx
biblium/additional files/template for tex output.xlsx
biblium/additional files/template for word output.xlsx
biblium/additional files/variable names.xlsx
biblium/additional files/variable_names.xlsx
biblium/additional files/icons/home.png
biblium/additional files/icons/logo-big.png
biblium/additional files/icons/logo.png
biblium/additional files/icons/plot.png
biblium/additional files/icons/table.png
biblium/addons/__init__.py
biblium/addons/addon_helpers.py
biblium/addons/advanced_statistics.py
biblium/addons/altmetrics.py
biblium-2.13.1.dist-info/METADATA
biblium-2.13.1.dist-info/WHEEL
biblium-2.13.1.dist-info/entry_points.txt
biblium-2.13.1.dist-info/top_level.txt
biblium-2.13.1.dist-info/RECORD
