Metadata-Version: 2.4
Name: biblium
Version: 2.13.1
Summary: Comprehensive Python library for bibliometric analysis of scientific literature
Author-email: Lan Umek <lan.umek@fu.uni-lj.si>
License: MIT
Project-URL: Homepage, https://github.com/lan-umek/biblium
Project-URL: Documentation, https://github.com/lan-umek/biblium#readme
Project-URL: Repository, https://github.com/lan-umek/biblium
Project-URL: Issues, https://github.com/lan-umek/biblium/issues
Keywords: bibliometrics,scientometrics,citation analysis,scopus,web of science,openalex,pubmed,network analysis,topic modeling
Classifier: Development Status :: 4 - Beta
Classifier: Intended Audience :: Science/Research
Classifier: License :: OSI Approved :: MIT License
Classifier: Programming Language :: Python :: 3
Classifier: Programming Language :: Python :: 3.9
Classifier: Programming Language :: Python :: 3.10
Classifier: Programming Language :: Python :: 3.11
Classifier: Programming Language :: Python :: 3.12
Classifier: Programming Language :: Python :: 3.13
Classifier: Programming Language :: Python :: 3.14
Classifier: Topic :: Scientific/Engineering :: Information Analysis
Classifier: Topic :: Text Processing :: General
Requires-Python: >=3.9
Requires-Dist: pandas>=1.5.0
Requires-Dist: numpy>=1.23.0
Requires-Dist: openpyxl>=3.0.0
Requires-Dist: xlsxwriter>=3.0.0
Requires-Dist: matplotlib>=3.6.0
Requires-Dist: seaborn>=0.12.0
Requires-Dist: pillow>=9.0.0
Requires-Dist: wordcloud>=1.9.0
Requires-Dist: adjustText>=0.8
Requires-Dist: squarify>=0.4.0
Requires-Dist: networkx>=2.8.0
Requires-Dist: nltk>=3.8.0
Requires-Dist: scikit-learn>=1.2.0
Requires-Dist: scipy>=1.10.0
Requires-Dist: statsmodels>=0.14.0
Requires-Dist: python-docx>=0.8.0
Requires-Dist: python-pptx>=0.6.0
Requires-Dist: reportlab>=4.0.0
Requires-Dist: requests>=2.28.0
Requires-Dist: tqdm>=4.65.0
Requires-Dist: thefuzz>=0.20.0
Requires-Dist: rapidfuzz>=3.0.0
Provides-Extra: llm
Requires-Dist: openai>=1.0.0; extra == "llm"
Requires-Dist: anthropic>=0.18.0; extra == "llm"
Requires-Dist: huggingface_hub>=0.19.0; extra == "llm"
Provides-Extra: nlp
Requires-Dist: gensim>=4.3.0; extra == "nlp"
Requires-Dist: spacy>=3.5.0; extra == "nlp"
Requires-Dist: sentence-transformers>=2.2.0; extra == "nlp"
Requires-Dist: bertopic>=0.15.0; extra == "nlp"
Requires-Dist: textblob>=0.17.0; extra == "nlp"
Requires-Dist: pyLDAvis>=3.4.0; extra == "nlp"
Requires-Dist: transformers>=4.30.0; extra == "nlp"
Provides-Extra: geo
Requires-Dist: geopandas>=0.12.0; extra == "geo"
Requires-Dist: folium>=0.14.0; extra == "geo"
Requires-Dist: geopy>=2.3.0; extra == "geo"
Requires-Dist: pycountry>=22.0.0; extra == "geo"
Requires-Dist: shapely>=2.0.0; extra == "geo"
Provides-Extra: interactive
Requires-Dist: bokeh>=3.0.0; extra == "interactive"
Requires-Dist: plotly>=5.0.0; extra == "interactive"
Requires-Dist: pyvis>=0.3.0; extra == "interactive"
Requires-Dist: holoviews>=1.15.0; extra == "interactive"
Provides-Extra: ml
Requires-Dist: xgboost>=1.7.0; extra == "ml"
Requires-Dist: lightgbm>=3.3.0; extra == "ml"
Requires-Dist: umap-learn>=0.5.0; extra == "ml"
Requires-Dist: prince>=0.8.0; extra == "ml"
Provides-Extra: network
Requires-Dist: python-igraph>=0.10.0; extra == "network"
Requires-Dist: python-louvain>=0.16; extra == "network"
Provides-Extra: extra
Requires-Dist: upsetplot>=0.8.0; extra == "extra"
Requires-Dist: venn>=0.1.3; extra == "extra"
Requires-Dist: matplotlib-venn>=0.11.0; extra == "extra"
Requires-Dist: powerlaw>=1.5.0; extra == "extra"
Requires-Dist: psutil>=5.9.0; extra == "extra"
Requires-Dist: pyyaml>=6.0.0; extra == "extra"
Requires-Dist: ratelimit>=2.2.0; extra == "extra"
Provides-Extra: full
Requires-Dist: biblium[extra,geo,interactive,llm,ml,network,nlp]; extra == "full"
Dynamic: requires-python
